Workbook
Name Slicer_Category: #N/A
Name Slicer_Category1: #N/A
Name Slicer_Region: #N/A
Name Slicer_Region1: #N/A

Sheet Final Project Dataset
A1: Transaction_ID | B1: Date | C1: Customer_ID | D1: Customer_Name | E1: Product_ID | F1: Product_Name | G1: Category | H1: Quantity | I1: Unit_Price | J1: Payment_Method | K1: Region | L1: Customer_Segment | M1: Customer_Since | N1: Total_Amount
A2: TRX0155 | B2: 45393 | C2: CUST023 | D2: Paul Baker | E2: P009 | F2: Monitor | G2: Electronics | H2: 3 | I2: 249.99 | J2: Cash | K2: Central | L2: Basic | M2: 44425 | N2: 749.97
A3: TRX0023 | B3: 45394 | C3: CUST013 | D3: Joseph Jackson | E3: P009 | F3: Monitor | G3: Electronics | H3: 3 | I3: 249.99 | J3: Credit Card | K3: Central | L3: Premium | M3: 44575 | N3: 749.97
A4: TRX0139 | B4: 45395 | C4: CUST021 | D4: Kevin Scott | E4: P005 | F4: Blender | G4: Appliances | H4: 3 | I4: 59.99 | J4: PayPal | K4: South | L4: Standard | M4: 45262 | N4: 179.97
A5: TRX0043 | B5: 45396 | C5: CUST046 | D5: Kathleen Bennett | E5: P005 | F5: Blender | G5: Appliances | H5: 3 | I5: 59.99 | J5: Cash | K5: North | L5: Premium | M5: 45114 | N5: 179.97
A6: TRX0212 | B6: 45397 | C6: CUST003 | D6: Michael Brown | E6: P008 | F6: Bookshelf | G6: Furniture | H6: 5 | I6: 149.99 | J6: Credit Card | K6: North | L6: Premium | M6: 45295 | N6: 749.95
A7: TRX0092 | B7: 45398 | C7: CUST024 | D7: Dorothy Nelson | E7: P005 | F7: Blender | G7: Appliances | H7: 2 | I7: 59.99 | J7: Cash | K7: West | L7: Standard | M7: 44746 | N7: 119.98
A8: TRX0193 | B8: 45399 | C8: CUST024 | D8: Dorothy Nelson | E8: P003 | F8: Headphones | G8: Electronics | H8: 5 | I8: 149.99 | J8: Credit Card | K8: Central | L8: Standard | M8: 44418 | N8: 749.95
A9: TRX0240 | B9: 45400 | C9: CUST017 | D9: Charles Allen | E9: P005 | F9: Blender | G9: Appliances | H9: 3 | I9: 59.99 | J9: Debit Card | K9: South | L9: Basic | M9: 45007 | N9: 179.97
A10: TRX0135 | B10: 45401 | C10: CUST009 | D10: Robert Thomas | E10: P001 | F10: Laptop | G10: Electronics | H10: 3 | I10: 899.99 | J10: PayPal | K10: East | L10: Standard | M10: 45299 | N10: 2699.97
A11: TRX0185 | B11: 45402 | C11: CUST026 | D11: Karen Hill | E11: P005 | F11: Blender | G11: Appliances | H11: 3 | I11: 59.99 | J11: Cash | K11: West | L11: Premium | M11: 45207 | N11: 179.97
A12: TRX0138 | B12: 45403 | C12: CUST022 | D12: Susan Green | E12: P008 | F12: Bookshelf | G12: Furniture | H12: 1 | I12: 149.99 | J12: Credit Card | K12: West | L12: Standard | M12: 45103 | N12: 149.99
A13: TRX0209 | B13: 45404 | C13: CUST046 | D13: Kathleen Bennett | E13: P008 | F13: Bookshelf | G13: Furniture | H13: 5 | I13: 149.99 | J13: Debit Card | K13: North | L13: Basic | M13: 44830 | N13: 749.95
... A251: TRX0064 | B251: 45642 | C251: CUST031 | D251: Steven Turner | E251: P010 | F251: Keyboard | G251: Electronics | H251: 3 | I251: 89.99 | J251: Debit Card | K251: North | L251: Premium | M251: 44878 | N251: 269.97

Sheet date time
A1: Transaction_ID | B1: Date | C1: Days_Since_Transaction | D1: Month_End | E1: Current_Time
A2: {=Table1[Transaction_ID]} -> TRX0155 | B2: {=Table1[Date]} -> 45393 | C2: =TODAY()-B2 -> 705 | D2: =EOMONTH(B2,0) -> 45412 | E2: =NOW() -> 46098.777
A3: TRX0023 | B3: 45394 | C3: =TODAY()-B3 -> 704 | D3: =EOMONTH(B3,0) -> 45412 | E3: =NOW() -> 46098.777
A4: TRX0139 | B4: 45395 | C4: =TODAY()-B4 -> 703 | D4: =EOMONTH(B4,0) -> 45412 | E4: =NOW() -> 46098.777
A5: TRX0043 | B5: 45396 | C5: =TODAY()-B5 -> 702 | D5: =EOMONTH(B5,0) -> 45412 | E5: =NOW() -> 46098.777
A6: TRX0212 | B6: 45397 | C6: =TODAY()-B6 -> 701 | D6: =EOMONTH(B6,0) -> 45412 | E6: =NOW() -> 46098.777
A7: TRX0092 | B7: 45398 | C7: =TODAY()-B7 -> 700 | D7: =EOMONTH(B7,0) -> 45412 | E7: =NOW() -> 46098.777
A8: TRX0193 | B8: 45399 | C8: =TODAY()-B8 -> 699 | D8: =EOMONTH(B8,0) -> 45412 | E8: =NOW() -> 46098.777
A9: TRX0240 | B9: 45400 | C9: =TODAY()-B9 -> 698 | D9: =EOMONTH(B9,0) -> 45412 | E9: =NOW() -> 46098.777
A10: TRX0135 | B10: 45401 | C10: =TODAY()-B10 -> 697 | D10: =EOMONTH(B10,0) -> 45412 | E10: =NOW() -> 46098.777
A11: TRX0185 | B11: 45402 | C11: =TODAY()-B11 -> 696 | D11: =EOMONTH(B11,0) -> 45412 | E11: =NOW() -> 46098.777
A12: TRX0138 | B12: 45403 | C12: =TODAY()-B12 -> 695 | D12: =EOMONTH(B12,0) -> 45412 | E12: =NOW() -> 46098.777
A13: TRX0209 | B13: 45404 | C13: =TODAY()-B13 -> 694 | D13: =EOMONTH(B13,0) -> 45412 | E13: =NOW() -> 46098.777
A14: TRX0246 | B14: 45405 | C14: =TODAY()-B14 -> 693 | D14: =EOMONTH(B14,0) -> 45412 | E14: =NOW() -> 46098.777
... A251: TRX0064 | B251: 45642 | C251: =TODAY()-B251 -> 456 | D251: =EOMONTH(B251,0) -> 45657 | E251: =NOW() -> 46098.777

Sheet filter
B3: highlighted one is formula
B4: finding customers through region using filter
B5: Transaction_ID | C5: Date | D5: Customer_ID | E5: Customer_Name | F5: Product_ID | G5: Product_Name | H5: Category | I5: Quantity | J5: Unit_Price | K5: Payment_Method | L5: Region | M5: Customer_Segment | N5: Customer_Since | O5: Total_Amount
B6: {=_xlfn._xlws.FILTER(Table1[],Table1[Region]="North")} -> TRX0043 | C6: 45396 | D6: CUST046 | E6: Kathleen Bennett | F6: P005 | G6: Blender | H6: Appliances | I6: 3 | J6: 59.99 | K6: Cash | L6: North | M6: Premium | N6: 45114 | O6: 179.97
B7: TRX0212 | C7: 45397 | D7: CUST003 | E7: Michael Brown | F7: P008 | G7: Bookshelf | H7: Furniture | I7: 5 | J7: 149.99 | K7: Credit Card | L7: North | M7: Premium | N7: 45295 | O7: 749.95
B8: TRX0209 | C8: 45404 | D8: CUST046 | E8: Kathleen Bennett | F8: P008 | G8: Bookshelf | H8: Furniture | I8: 5 | J8: 149.99 | K8: Debit Card | L8: North | M8: Basic | N8: 44830 | O8: 749.95
B9: TRX0246 | C9: 45405 | D9: CUST041 | E9: Peter Richardson | F9: P008 | G9: Bookshelf | H9: Furniture | I9: 3 | J9: 149.99 | K9: Cash | L9: North | M9: Premium | N9: 44806 | O9: 449.97
B10: TRX0067 | C10: 45406 | D10: CUST043 | E10: Dennis Gray | F10: P005 | G10: Blender | H10: Appliances | I10: 3 | J10: 59.99 | K10: Credit Card | L10: North | M10: Standard | N10: 45351 | O10: 179.97
B11: TRX0230 | C11: 45408 | D11: CUST027 | E11: George Adams | F11: P001 | G11: Laptop | H11: Electronics | I11: 1 | J11: 899.99 | K11: Debit Card | L11: North | M11: Standard | N11: 44920 | O11: 899.99
B12: TRX0049 | C12: 45409 | D12: CUST025 | E12: Mark Carter | F12: P008 | G12: Bookshelf | H12: Furniture | I12: 4 | J12: 149.99 | K12: Debit Card | L12: North | M12: Premium | N12: 45374 | O12: 599.96
B13: TRX0134 | C13: 45410 | D13: CUST010 | E13: Maria Garcia | F13: P002 | G13: Smartphone | H13: Electronics | I13: 2 | J13: 699.99 | K13: Cash | L13: North | M13: Basic | N13: 44781 | O13: 1399.98
B14: TRX0222 | C14: 45412 | D14: CUST048 | E14: Virginia Sanders | F14: P009 | G14: Monitor | H14: Electronics | I14: 3 | J14: 249.99 | K14: Credit Card | L14: North | M14: Premium | N14: 45224 | O14: 749.97
B15: TRX0204 | C15: 45415 | D15: CUST044 | E15: Cynthia Price | F15: P009 | G15: Monitor | H15: Electronics | I15: 4 | J15: 249.99 | K15: PayPal | L15: North | M15: Standard | N15: 44468 | O15: 999.96
B16: TRX0004 | C16: 45420 | D16: CUST012 | E16: Patricia Moore | F16: P010 | G16: Keyboard | H16: Electronics | I16: 5 | J16: 89.99 | K16: Cash | L16: North | M16: Premium | N16: 44919 | O16: 449.95
B17: TRX0245 | C17: 45429 | D17: CUST031 | E17: Steven Turner | F17: P006 | G17: Office Chair | H17: Furniture | I17: 3 | J17: 199.99 | K17: Credit Card | L17: North | M17: Premium | N17: 45292 | O17: 599.97
B18: TRX0042 | C18: 45432 | D18: CUST019 | E18: Daniel King | F18: P004 | G18: Coffee Maker | H18: Appliances | I18: 1 | J18: 79.99 | K18: Cash | L18: North | M18: Standard | N18: 44917 | O18: 79.99
... B64: TRX0064 | C64: 45642 | D64: CUST031 | E64: Steven Turner | F64: P010 | G64: Keyboard | H64: Electronics | I64: 3 | J64: 89.99 | K64: Debit Card | L64: North | M64: Premium | N64: 44878 | O64: 269.97

Sheet conditional format
A1: Customer_ID | B1: Customer_Name | C1: Total_Amount
A2: CUST023 | B2: Paul Baker | C2: 749.97
A3: CUST013 | B3: Joseph Jackson | C3: 749.97
A4: CUST021 | B4: Kevin Scott | C4: 179.97
A5: CUST046 | B5: Kathleen Bennett | C5: 179.97
A6: CUST003 | B6: Michael Brown | C6: 749.95
A7: CUST024 | B7: Dorothy Nelson | C7: 119.98
A8: CUST024 | B8: Dorothy Nelson | C8: 749.95
A9: CUST017 | B9: Charles Allen | C9: 179.97
A10: CUST009 | B10: Robert Thomas | C10: 2699.97
A11: CUST026 | B11: Karen Hill | C11: 179.97
A12: CUST022 | B12: Susan Green | C12: 149.99
A13: CUST046 | B13: Kathleen Bennett | C13: 749.95
... A251: CUST031 | B251: Steven Turner | C251: 269.97

Sheet WHAT IF
A1: Quantity | B1: Unit_Price | C1: Total_Amount | F1: WHAT IF USING GOAL SEEK
A2: 3 | B2: 249.99 | C2: 749.97
A3: 3 | B3: 249.99 | C3: 749.97
A4: 3 | B4: 59.99 | C4: 179.97 | F4: EX | G4: PRODUCT | H4: QTY | I4: PRICE | J4: REVNUE
A5: 3 | B5: 59.99 | C5: 179.97 | G5: MIC | H5: 66.666667 | I5: 15000 | J5: =H5*I5 -> 1000000
A6: 5 | B6: 149.99 | C6: 749.95
A7: 2 | B7: 59.99 | C7: 119.98 | F7: I WANT SALES 20 LAKH | G7: PRODUCT | H7: QTY | I7: PRICE | J7: REVNUE
A8: 5 | B8: 149.99 | C8: 749.95 | G8: MIC | H8: 133.33333 | I8: 15000 | J8: =H8*I8 -> 2000000
A9: 3 | B9: 59.99 | C9: 179.97
A10: 3 | B10: 899.99 | C10: 2699.97
A11: 3 | B11: 59.99 | C11: 179.97
A12: 1 | B12: 149.99 | C12: 149.99
A13: 5 | B13: 149.99 | C13: 749.95
A14: 3 | B14: 149.99 | C14: 449.97
A15: 3 | B15: 59.99 | C15: 179.97
A16: 3 | B16: 699.99 | C16: 2099.97
A17: 1 | B17: 899.99 | C17: 899.99
A18: 4 | B18: 149.99 | C18: 599.96
A19: 2 | B19: 699.99 | C19: 1399.98
A20: 4 | B20: 899.99 | C20: 3599.96
... A22: 5 | B22: 699.99 | C22: 3499.95

Sheet LINEAR REGRESISON
A1: Quantity | B1: Unit_Price | C1: Total_Amount
A2: 3 | B2: 249.99 | C2: 749.97 | J2: LINEAR REGRESSION
A3: 3 | B3: 249.99 | C3: 749.97
A4: 3 | B4: 59.99 | C4: 179.97 | J4: Regression Statistics
A5: 3 | B5: 59.99 | C5: 179.97 | J5: Multiple R | K5: 0.1083936
A6: 5 | B6: 149.99 | C6: 749.95 | J6: R Square | K6: 0.011749172
A7: 2 | B7: 59.99 | C7: 119.98 | J7: Adjusted R Square | K7: -0.04026403
A8: 5 | B8: 149.99 | C8: 749.95 | J8: Standard Error | K8: 325.39824
A9: 3 | B9: 59.99 | C9: 179.97 | J9: Observations | K9: 21
A10: 3 | B10: 899.99 | C10: 2699.97
A11: 3 | B11: 59.99 | C11: 179.97 | J11: ANOVA
A12: 1 | B12: 149.99 | C12: 149.99 | K12: df | L12: SS | M12: MS | N12: F | O12: Significance F
A13: 5 | B13: 149.99 | C13: 749.95 | J13: Regression | K13: 1 | L13: 23917.957 | M13: 23917.957 | N13: 0.22588827 | O13: 0.64000762
A14: 3 | B14: 149.99 | C14: 449.97 | J14: Residual | K14: 19 | L14: 2011796.3 | M14: 105884.02
A15: 3 | B15: 59.99 | C15: 179.97 | J15: Total | K15: 20 | L15: 2035714.3
A16: 3 | B16: 699.99 | C16: 2099.97
A17: 1 | B17: 899.99 | C17: 899.99 | K17: Coefficients | L17: Standard Error | M17: t Stat | N17: P-value | O17: Lower 95% | P17: Upper 95% | Q17: Lower 95.0% | R17: Upper 95.0%
A18: 4 | B18: 149.99 | C18: 599.96 | J18: Intercept | K18: 418.81867 | L18: 211.21546 | M18: 1.9828978 | N18: 0.062025062 | O18: -23.260376 | P18: 860.89772 | Q18: -23.260376 | R18: 860.89772
A19: 2 | B19: 699.99 | C19: 1399.98 | J19: X Variable 1 | K19: -29.632867 | L19: 62.348619 | M19: -0.47527704 | N19: 0.64000762 | O19: -160.13003 | P19: 100.86429 | Q19: -160.13003 | R19: 100.86429
A20: 4 | B20: 899.99 | C20: 3599.96
A21: 3 | B21: 249.99 | C21: 749.97
A22: 5 | B22: 699.99 | C22: 3499.95

Sheet GROUP BY
A1: UNIQUE_CUSTOMERS | B1: total_spend | C1: typee
A2: {=_xlfn.UNIQUE(Table1[Customer_Name],TRUE)} -> Paul Baker | B2: =SUMIFS(Table1[Total_Amount],Table1[Customer_Name],A2) -> 8309.74 | C2: =IF(B2>2000,"high value","Normal") -> high value
A3: Joseph Jackson | B3: =SUMIFS(Table1[Total_Amount],Table1[Customer_Name],A3) -> 6949.84 | C3: =IF(B3>2000,"high value","Normal") -> high value
A4: Kevin Scott | B4: =SUMIFS(Table1[Total_Amount],Table1[Customer_Name],A4) -> 3259.87 | C4: =IF(B4>2000,"high value","Normal") -> high value
A5: Kathleen Bennett | B5: =SUMIFS(Table1[Total_Amount],Table1[Customer_Name],A5) -> 4309.81 | C5: =IF(B5>2000,"high value","Normal") -> high value
A6: Michael Brown | B6: =SUMIFS(Table1[Total_Amount],Table1[Customer_Name],A6) -> 6169.74 | C6: =IF(B6>2000,"high value","Normal") -> high value
A7: Dorothy Nelson | B7: =SUMIFS(Table1[Total_Amount],Table1[Customer_Name],A7) -> 8269.79 | C7: =IF(B7>2000,"high value","Normal") -> high value
A8: Dorothy Nelson | B8: =SUMIFS(Table1[Total_Amount],Table1[Customer_Name],A8) -> 8269.79 | C8: =IF(B8>2000,"high value","Normal") -> high value
A9: Charles Allen | B9: =SUMIFS(Table1[Total_Amount],Table1[Customer_Name],A9) -> 5089.73 | C9: =IF(B9>2000,"high value","Normal") -> high value
A10: Robert Thomas | B10: =SUMIFS(Table1[Total_Amount],Table1[Customer_Name],A10) -> 3509.9 | C10: =IF(B10>2000,"high value","Normal") -> high value
A11: Karen Hill | B11: =SUMIFS(Table1[Total_Amount],Table1[Customer_Name],A11) -> 8009.77 | C11: =IF(B11>2000,"high value","Normal") -> high value
A12: Susan Green | B12: =SUMIFS(Table1[Total_Amount],Table1[Customer_Name],A12) -> 1979.89 | C12: =IF(B12>2000,"high value","Normal") -> Normal
A13: Kathleen Bennett | B13: =SUMIFS(Table1[Total_Amount],Table1[Customer_Name],A13) -> 4309.81 | C13: =IF(B13>2000,"high value","Normal") -> high value
A14: Peter Richardson | B14: =SUMIFS(Table1[Total_Amount],Table1[Customer_Name],A14) -> 5949.85 | C14: =IF(B14>2000,"high value","Normal") -> high value
... A251: Steven Turner | B251: =SUMIFS(Table1[Total_Amount],Table1[Customer_Name],A251) -> 2649.83 | C251: =IF(B251>2000,"high value","Normal") -> high value

Sheet product
A1: unique_product | B1: count_purchases | C1: total _sales_prodct
A2: {=_xlfn.UNIQUE(Table1[Product_Name])} -> Monitor | B2: =COUNTIFS(Table1[Product_Name],A2) -> 26 | C2: =SUMIFS(Table1[Total_Amount],Table1[Product_Name],product!A2) -> 21999.12
A3: Blender | B3: =COUNTIFS(Table1[Product_Name],A3) -> 29 | C3: =SUMIFS(Table1[Total_Amount],Table1[Product_Name],product!A3) -> 5219.13
A4: Bookshelf | B4: =COUNTIFS(Table1[Product_Name],A4) -> 35 | C4: =SUMIFS(Table1[Total_Amount],Table1[Product_Name],product!A4) -> 15298.98
A5: Headphones | B5: =COUNTIFS(Table1[Product_Name],A5) -> 16 | C5: =SUMIFS(Table1[Total_Amount],Table1[Product_Name],product!A5) -> 7049.53
A6: Laptop | B6: =COUNTIFS(Table1[Product_Name],A6) -> 24 | C6: =SUMIFS(Table1[Total_Amount],Table1[Product_Name],product!A6) -> 67499.25
A7: Smartphone | B7: =COUNTIFS(Table1[Product_Name],A7) -> 31 | C7: =SUMIFS(Table1[Total_Amount],Table1[Product_Name],product!A7) -> 67199.04
A8: Desk | B8: =COUNTIFS(Table1[Product_Name],A8) -> 26 | C8: =SUMIFS(Table1[Total_Amount],Table1[Product_Name],product!A8) -> 23399.22
A9: Coffee Maker | B9: =COUNTIFS(Table1[Product_Name],A9) -> 14 | C9: =SUMIFS(Table1[Total_Amount],Table1[Product_Name],product!A9) -> 3119.61
A10: Keyboard | B10: =COUNTIFS(Table1[Product_Name],A10) -> 34 | C10: =SUMIFS(Table1[Total_Amount],Table1[Product_Name],product!A10) -> 8009.11
A11: Office Chair | B11: =COUNTIFS(Table1[Product_Name],A11) -> 15 | C11: =SUMIFS(Table1[Total_Amount],Table1[Product_Name],product!A11) -> 10399.48

Sheet lists
A1: A | B1: B | D1: yes/no
A2: Paul Baker | B2: Kevin Scott | D2: =IF(ISNUMBER(MATCH(A2,B2:B4,0)),"match","-") -> match
A3: Joseph Jackson | B3: Maria Garcia | D3: =IF(ISNUMBER(MATCH(A3,B3:B5,0)),"match","-") -> -
A4: Kevin Scott | B4: Paul Baker | D4: =IF(ISNUMBER(MATCH(A4,B4:B6,0)),"match","-") -> -

Sheet abbreviations
B2: customer_name | C2: result
B3: rahul sharma | C3: =LEFT(B3,1)&LEFT(MID(B3,FIND(" ",B3)+1,10),1) -> rs
B4: preeti sharma | C4: =LEFT(B4,1)&LEFT(MID(B4,FIND(" ",B4)+1,10),1) -> ps
B5: james mikaelson | C5: =LEFT(B5,1)&LEFT(MID(B5,FIND(" ",B5)+1,10),1) -> jm
B6: mike ross | C6: =LEFT(B6,1)&LEFT(MID(B6,FIND(" ",B6)+1,10),1) -> mr
B7: stefan salvatore | C7: =LEFT(B7,1)&LEFT(MID(B7,FIND(" ",B7)+1,10),1) -> ss

Sheet pivot tables
B2: Region | C2: Sum of Total_Amount | G2: Product_Name | H2: Sum of Quantity
B3: Central | C3: 41288.34 | G3: Blender | H3: 87 | M3: Region | N3: Category | O3: Sum of Total_Amount
B4: East | C4: 59288.39 | G4: Bookshelf | H4: 102 | M4: Central | N4: Appliances | O4: 1999.71
B5: North | C5: 50808.31 | G5: Coffee Maker | H5: 39 | N5: Electronics | O5: 24889.33
B6: West | C6: 41408.68 | G6: Desk | H6: 78 | N6: Furniture | O6: 14399.3
B7: Grand Total | C7: 192793.72 | G7: Headphones | H7: 47 | M7: Central Total | O7: 41288.34
G8: Keyboard | H8: 89 | M8: East | N8: Appliances | O8: 2239.67
G9: Laptop | H9: 75 | N9: Electronics | O9: 50649.01
G10: Monitor | H10: 88 | N10: Furniture | O10: 6399.71
G11: Office Chair | H11: 52 | M11: East Total | O11: 59288.39
G12: Smartphone | H12: 96 | M12: North | N12: Appliances | O12: 1119.84
G13: Grand Total | H13: 753 | N13: Electronics | O13: 39239.04
N14: Furniture | O14: 10449.43
M15: North Total | O15: 50808.31
M16: South | N16: Appliances | O16: 1099.83
N17: Electronics | O17: 25549.32
N18: Furniture | O18: 9749.6
M19: South Total | O19: 36398.75
M20: West | N20: Appliances | O20: 1879.69
N21: Electronics | O21: 31429.35
N22: Furniture | O22: 8099.64
M23: West Total | O23: 41408.68
M24: Grand Total | O24: 229192.47

Sheet Dashboard
